block_generator/__init__.py
block_generator/block_generator.py
block_generator/block_organizer.py
block_generator/soundont_tester.py
block_generator/violino_conf.py
block_generator/block_parser/__init__.py
block_generator/block_parser/block_parser.py
block_generator/block_parser/chord_handler.py
block_generator/block_parser/instrument_handler.py
block_generator/block_parser/instruments.json
block_generator/block_parser/markov_values.py
block_generator/block_parser/midi_handler.py
block_generator/block_parser/note_generator.py
block_generator/block_parser/timing_organizer.py
block_generator/song_namer/__init__.py
block_generator/song_namer/ninoinator.py
nino_violino-0.0.13.dist-info/METADATA
nino_violino-0.0.13.dist-info/RECORD
nino_violino-0.0.13.dist-info/WHEEL
nino_violino-0.0.13.dist-info/top_level.txt
