Metadata-Version: 2.1
Name: nino-violino
Version: 0.0.13
Summary: Yet another music generator. 
Home-page: UNKNOWN
Author: Nikola Dokoski
Author-email: UNKNOWN
License: UNKNOWN
Keywords: nino_violino
Platform: UNKNOWN
Requires-Dist: midiutil
Requires-Dist: haikunator
